keywordx/__init__.py
keywordx/chunker.py
keywordx/embeddings.py
keywordx/extractor.py
keywordx/idf.py
keywordx/matcher.py
keywordx/ner.py
keywordx/pipeline.py
keywordx/utils.py
keywordx-1.0.5.dist-info/licenses/LICENSE.txt
keywordx-1.0.5.dist-info/METADATA
keywordx-1.0.5.dist-info/WHEEL
keywordx-1.0.5.dist-info/top_level.txt
keywordx-1.0.5.dist-info/RECORD
