Metadata-Version: 2.4
Name: keywordx
Version: 1.0.5
Summary: A Python library for extracting and matching keywords with semantic and entity-based boosting.
Author: Madhusudan
Author-email: Madhusudan <dmpathani@gmail.com>, Saniya Naaz <saniyanaaz2k4@gmail.com>, "Dr. Nandeeswar S B" <hodcse.aiml@amceducation.in>
License: MIT
Project-URL: Homepage, https://github.com/keikurono7/keywordx
Project-URL: Documentation, https://github.com/keikurono7/keywordx#readme
Keywords: keyword extraction,NLP,semantic matching
Classifier: Programming Language :: Python :: 3
Classifier: License :: OSI Approved :: MIT License
Classifier: Operating System :: OS Independent
Requires-Python: >=3.7
License-File: LICENSE.txt
Requires-Dist: spacy>=3.6
Requires-Dist: numpy>=1.19.5
Requires-Dist: dateparser>=1.1.0
Dynamic: license-file
